slack_scim/__init__.py
slack_scim/v1/__init__.py
slack_scim/v1/client.py
slack_scim/v1/errors.py
slack_scim/v1/group.py
slack_scim/v1/groups.py
slack_scim/v1/request.py
slack_scim/v1/response.py
slack_scim/v1/service_provider_configs.py
slack_scim/v1/user.py
slack_scim/v1/users.py
slack_scim/v1/version.py
slack_scim-1.1.0.dist-info/LICENSE
slack_scim-1.1.0.dist-info/METADATA
slack_scim-1.1.0.dist-info/WHEEL
slack_scim-1.1.0.dist-info/top_level.txt
slack_scim-1.1.0.dist-info/RECORD
