Metadata-Version: 2.1
Name: slack-scim
Version: 1.1.0
Summary: Slack SCIM API Client
Home-page: https://github.com/seratch/python-slack-scim
Author: Kazuhiro Sera
Author-email: seratch@gmail.com
License: UNKNOWN
Platform: UNKNOWN
Classifier: Programming Language :: Python :: 3.6
Classifier: Programming Language :: Python :: 3.7
Classifier: Programming Language :: Python :: 3.8
Classifier: Programming Language :: Python :: Implementation :: CPython
Classifier: License :: OSI Approved :: MIT License
Classifier: Operating System :: OS Independent
Requires-Python: >=3.6
